fastarithmetic/__init__.py
fastarithmetic/operations.py
fastarithmetic-2.0.0.dist-info/METADATA
fastarithmetic-2.0.0.dist-info/WHEEL
fastarithmetic-2.0.0.dist-info/top_level.txt
fastarithmetic-2.0.0.dist-info/RECORD
