Metadata-Version: 2.2
Name: fastarithmetic
Version: 2.0.0
Summary: Optimized arithmetic operations for large numbers with high-speed algorithms.
Home-page: https://github.com/Sivatech24/fastarithmetic
Author: CodingMaster24
Author-email: sivatech24@gmail.com
Classifier: Programming Language :: Python :: 3
Classifier: License :: OSI Approved :: MIT License
Classifier: Operating System :: OS Independent
Requires-Python: >=3.8
Dynamic: author
Dynamic: author-email
Dynamic: classifier
Dynamic: description
Dynamic: home-page
Dynamic: requires-python
Dynamic: summary
